the37lab_authlib/__init__.py
the37lab_authlib/_git_version.txt
the37lab_authlib/auth.py
the37lab_authlib/db.py
the37lab_authlib/decorators.py
the37lab_authlib/exceptions.py
the37lab_authlib/models.py
the37lab_authlib-0.1.1769444872.dist-info/METADATA
the37lab_authlib-0.1.1769444872.dist-info/WHEEL
the37lab_authlib-0.1.1769444872.dist-info/top_level.txt
the37lab_authlib-0.1.1769444872.dist-info/RECORD
