Metadata-Version: 2.4
Name: the37lab_authlib
Version: 0.1.1769444872
Summary: Python SDK for the Authlib
Author-email: the37lab <info@the37lab.com>
Classifier: Programming Language :: Python :: 3
Classifier: Operating System :: OS Independent
Requires-Python: >=3.9
Requires-Dist: flask
Requires-Dist: psycopg2-binary
Requires-Dist: pyjwt
Requires-Dist: python-dotenv
Requires-Dist: requests
Requires-Dist: authlib
Requires-Dist: bcrypt
Requires-Dist: msal
Requires-Dist: slack-sdk
Requires-Dist: cachetools
